{
    "documentVersion": "0.0.1",
    "jsonSchemaSemanticVersion" : "1.1.0",
    "definitions" : [
      {
        "entityName" : "Document",
        "displayName" : "Document",
        "hasAttributes" : [
          {
            "name" : "documentId",
            "purpose" : "identifiedBy",
            "dataType" : "integer"
          },
          {
            "name" : "documentName",
            "purpose" : "hasA",
            "dataType" : "string",
            "description" : ""
          },
          {
            "name" : "documentType",
            "purpose" : "hasA",
            "dataType" : "string",
            "description" : ""
          },
          {
            "name" : "uploadedBy",
            "purpose" : "hasA",
            "dataType" : "string",
            "description" : ""
          },
          {
            "name" : "uploadedDate",
            "purpose" : "hasA",
            "dataType" : "string",
            "description" : ""
          },
          {
            "name" : "fileURL",
            "purpose" : "hasA",
            "dataType" : "string",
            "description" : ""
          },
          {
            "name" : "fileType",
            "purpose" : "hasA",
            "dataType" : "string",
            "description" : ""
          },
          {
            "name" : "fileSize",
            "purpose" : "hasA",
            "dataType" : "string",
            "description" : ""
          },
          {
            "name" : "versionNumber",
            "purpose" : "hasA",
            "dataType" : "string",
            "description" : ""
          },
          {
            "name" : "status",
            "purpose" : "hasA",
            "dataType" : "string",
            "description" : ""
          },
          {
            "name" : "notes",
            "purpose" : "hasA",
            "dataType" : "string",
            "description" : ""
          },
          {
            "name" : "lastModifiedBy",
            "purpose" : "hasA",
            "dataType" : "string",
            "description" : ""
          },
          {
            "name" : "lastModifiedDate",
            "purpose" : "hasA",
            "dataType" : "string",
            "description" : ""
          },
          {
            "explanation" : "",
            "entity" : {
              "entityReference" : "Contract",
              "appliedTraits" : [
                {
                  "traitReference" : "is.identifiedBy",
                  "arguments" : [
                    "Contract/(resolvedAttributes)/contractId"
                  ]
                }
              ]
            },
            "name" : "contractId",
            "resolutionGuidance" : {
              "renameFormat" : "{m}",
              "entityByReference" : {
                "allowReference" : true,
                "foreignKeyAttribute" : {
                  "name" : "contractId",
                  "purpose" : "hasA",
                  "dataType" : "integer"
                }
              }
            }
          }
        ]
      }
    ]
  }
  