{
  "documentVersion": "0.0.1",
  "jsonSchemaSemanticVersion" : "1.1.0",
  "definitions" : [
    {
      "entityName" : "PayComponent",
      "displayName" : "PayComponent",
      "hasAttributes" : [
        {
          "name" : "Id",
          "purpose" : "identifiedBy",
          "dataType" : "string",
          "isNullable" : true,
          "description" : ""
        },
        {
          "name" : "CompanyId",
          "purpose" : "hasA",
          "dataType" : "string",
          "isNullable" : true,
          "description" : ""
        },
        {
          "name" : "Name",
          "purpose" : "hasA",
          "dataType" : "string",
          "isNullable" : true,
          "description" : ""
        },
        {
          "name" : "Description",
          "purpose" : "hasA",
          "dataType" : "string",
          "isNullable" : true,
          "description" : ""
        },
        {
          "name" : "Code",
          "purpose" : "hasA",
          "dataType" : "string",
          "isNullable" : true,
          "description" : ""
        },
        {
          "name" : "Type",
          "purpose" : "hasA",
          "dataType" : "string",
          "isNullable" : true,
          "description" : ""
        },
        {
          "name" : "IsTaxable",
          "purpose" : "hasA",
          "dataType" : "boolean",
          "isNullable" : true,
          "description" : ""
        },
        {
          "name" : "Amount",
          "purpose" : "hasA",
          "dataType" : "double",
          "isNullable" : true,
          "description" : ""
        },
        {
          "name" : "Rate",
          "purpose" : "hasA",
          "dataType" : "double",
          "isNullable" : true,
          "description" : ""
        },
        {
          "name" : "Units",
          "purpose" : "hasA",
          "dataType" : "double",
          "isNullable" : true,
          "description" : ""
        },
        {
          "name" : "UnitsType",
          "purpose" : "hasA",
          "dataType" : "string",
          "isNullable" : true,
          "description" : ""
        },
        {
          "name" : "ParentId",
          "purpose" : "hasA",
          "dataType" : "string",
          "isNullable" : true,
          "description" : ""
        },
        {
          "name" : "CalculationMethod",
          "purpose" : "hasA",
          "dataType" : "string",
          "isNullable" : true,
          "description" : ""
        },
        {
          "name" : "Frequency",
          "purpose" : "hasA",
          "dataType" : "string",
          "isNullable" : true,
          "description" : ""
        },
        {
          "name" : "EffectiveFromDate",
          "purpose" : "hasA",
          "dataType" : "dateTime",
          "isNullable" : true,
          "description" : ""
        },
        {
          "name" : "EffectiveToDate",
          "purpose" : "hasA",
          "dataType" : "dateTime",
          "isNullable" : true,
          "description" : ""
        },
        {
          "name" : "EffectOnPay",
          "purpose" : "hasA",
          "dataType" : "string",
          "isNullable" : true,
          "description" : ""
        },
        {
          "name" : "ApplicableWorkerTypes",
          "purpose" : "hasA",
          "dataType" : "string",
          "isNullable" : true,
          "description" : ""
        },
        {
          "name" : "Active",
          "purpose" : "hasA",
          "dataType" : "boolean",
          "isNullable" : true,
          "description" : ""
        },
        {
          "name" : "CreatedDate",
          "purpose" : "hasA",
          "dataType" : "dateTime",
          "isNullable" : true,
          "description" : ""
        },
        {
          "name" : "CreatedBy",
          "purpose" : "hasA",
          "dataType" : "string",
          "isNullable" : true,
          "description" : ""
        },
        {
          "name" : "UpdatedDate",
          "purpose" : "hasA",
          "dataType" : "dateTime",
          "isNullable" : true,
          "description" : ""
        },
        {
          "name" : "UpdatedBy",
          "purpose" : "hasA",
          "dataType" : "string",
          "isNullable" : true,
          "description" : ""
        },
        {
          "name" : "DeletedDate",
          "purpose" : "hasA",
          "dataType" : "dateTime",
          "isNullable" : true,
          "description" : ""
        },
        {
          "name" : "DeletedBy",
          "purpose" : "hasA",
          "dataType" : "string",
          "isNullable" : true,
          "description" : ""
        },
        {
          "name" : "Deleted",
          "purpose" : "hasA",
          "dataType" : "boolean",
          "isNullable" : true,
          "description" : ""
        }
      ]
    }
  ]
}